python_worker_extension/__init__.py
python_worker_extension_timer-1.0.2.dist-info/METADATA
python_worker_extension_timer-1.0.2.dist-info/WHEEL
python_worker_extension_timer-1.0.2.dist-info/top_level.txt
python_worker_extension_timer-1.0.2.dist-info/RECORD
