Metadata-Version: 2.1
Name: python-worker-extension-timer
Version: 1.0.2
Summary: Python Worker Extension Demo
Home-page: https://your-github-or-pypi-link
Author: Gordon
Author-email: gordon.hamilton@datadoghq.com
License: MIT
Classifier: Intended Audience :: End Users/Desktop
Classifier: Development Status :: 5 - Production/Stable
Classifier: Intended Audience :: End Users/Desktop
Classifier: License :: OSI Approved :: Apache Software License
Classifier: Programming Language :: Python
Classifier: Programming Language :: Python :: 3.7
Classifier: Programming Language :: Python :: 3.8
Classifier: Programming Language :: Python :: 3.9
Classifier: Programming Language :: Python :: 3.10
